{
  "recentFiles": [
    {
      "basename": "English",
      "path": "subjects lec-Log/English.md"
    },
    {
      "basename": "classical dances",
      "path": "3-FINAL notes/4.Statics GK/classical dances.md"
    },
    {
      "basename": "2025-04-13",
      "path": "1-Daily/2025-04-13.md"
    },
    {
      "basename": "2. Indus Valley Civilization",
      "path": "3-FINAL notes/3.History/1.Ancient history/2. Indus Valley Civilization.md"
    },
    {
      "basename": "6. Pre-Mauryan Age",
      "path": "3-FINAL notes/3.History/1.Ancient history/6. Pre-Mauryan Age.md"
    },
    {
      "basename": "7. Mauryan Empire",
      "path": "3-FINAL notes/3.History/1.Ancient history/7. Mauryan Empire.md"
    },
    {
      "basename": "1. Periods of HISTORY",
      "path": "3-FINAL notes/3.History/1.Ancient history/1. Periods of HISTORY.md"
    },
    {
      "basename": "3. Aryans & The Vedic Ages (1500 - 600 BC)",
      "path": "3-FINAL notes/3.History/1.Ancient history/3. Aryans & The Vedic Ages (1500 - 600 BC).md"
    },
    {
      "basename": "2025-04-12",
      "path": "1-Daily/2025-04-12.md"
    },
    {
      "basename": "important granth",
      "path": "3-FINAL notes/3.History/1.Ancient history/important granth.pdf"
    },
    {
      "basename": "4. Ancient history of India",
      "path": "3-FINAL notes/3.History/1.Ancient history/4. Ancient history of India.md"
    },
    {
      "basename": "1.Introduction",
      "path": "3-FINAL notes/3.History/1.Introduction.md"
    },
    {
      "basename": "wrong spelled word by me",
      "path": "3-FINAL notes/Zenglish/wrong spelled word by me.md"
    },
    {
      "basename": "verb-forms",
      "path": "3-FINAL notes/Zenglish/verb-forms.pdf"
    },
    {
      "basename": "6. Part-1 Union State and territories",
      "path": "3-FINAL notes/2.POLITY/6. Part-1 Union State and territories.md"
    },
    {
      "basename": "cloze test",
      "path": "3-FINAL notes/Zenglish/cloze test.md"
    },
    {
      "basename": "2025-04-11",
      "path": "1-Daily/2025-04-11.md"
    },
    {
      "basename": "5. preamble or Prastavna",
      "path": "3-FINAL notes/2.POLITY/5. preamble or Prastavna.md"
    },
    {
      "basename": "4. Salient features of Indian constitution",
      "path": "3-FINAL notes/2.POLITY/4. Salient features of Indian constitution.md"
    },
    {
      "basename": "2025-04-09",
      "path": "1-Daily/2025-04-09.md"
    },
    {
      "basename": "5. Jainism & Buddhism",
      "path": "3-FINAL notes/3.History/1.Ancient history/5. Jainism & Buddhism.md"
    },
    {
      "basename": "Math",
      "path": "subjects lec-Log/Math.md"
    },
    {
      "basename": "2025-04-07",
      "path": "1-Daily/2025-04-07.md"
    },
    {
      "basename": "2025-04-06",
      "path": "1-Daily/2025-04-06.md"
    },
    {
      "basename": "2025-04-05",
      "path": "1-Daily/2025-04-05.md"
    },
    {
      "basename": "Census",
      "path": "3-FINAL notes/4.Statics GK/Census.md"
    },
    {
      "basename": "Index of HiSTORY",
      "path": "3-FINAL notes/3.History/Index of HiSTORY.md"
    },
    {
      "basename": "RS Sharma (Class PPTs) export (1)",
      "path": "assests/RS Sharma (Class PPTs) export (1).pdf"
    },
    {
      "basename": "2025-04-04",
      "path": "1-Daily/2025-04-04.md"
    },
    {
      "basename": "Pasted image 20250122224328",
      "path": "assests/Pasted image 20250122224328.png"
    },
    {
      "basename": "Pasted image 20250122225725",
      "path": "assests/Pasted image 20250122225725.png"
    },
    {
      "basename": "2025-04-03",
      "path": "1-Daily/2025-04-03.md"
    },
    {
      "basename": "Screenshot_20250126-181702",
      "path": "assests/Screenshot_20250126-181702.jpeg"
    },
    {
      "basename": "2025-04-02",
      "path": "1-Daily/2025-04-02.md"
    },
    {
      "basename": "2025-04-01",
      "path": "1-Daily/2025-04-01.md"
    },
    {
      "basename": "discovery and vacancies",
      "path": "2-Review Notes/discovery and vacancies.md"
    },
    {
      "basename": "2025-03-30",
      "path": "1-Daily/2025-03-30.md"
    },
    {
      "basename": "reasoning",
      "path": "subjects lec-Log/reasoning.md"
    },
    {
      "basename": "2025-03-27",
      "path": "1-Daily/2025-03-27.md"
    },
    {
      "basename": "2025-03-26",
      "path": "1-Daily/2025-03-26.md"
    },
    {
      "basename": "2025-03-25",
      "path": "1-Daily/2025-03-25.md"
    },
    {
      "basename": "2025-03-23",
      "path": "1-Daily/2025-03-23.md"
    },
    {
      "basename": "2025-03-22",
      "path": "1-Daily/2025-03-22.md"
    },
    {
      "basename": "2025-03-21",
      "path": "1-Daily/2025-03-21.md"
    },
    {
      "basename": "2025-03-19",
      "path": "1-Daily/2025-03-19.md"
    },
    {
      "basename": "2025-03-18",
      "path": "1-Daily/2025-03-18.md"
    },
    {
      "basename": "2025-03-17",
      "path": "1-Daily/2025-03-17.md"
    },
    {
      "basename": "2025-03-16",
      "path": "1-Daily/2025-03-16.md"
    },
    {
      "basename": "2025-02-17",
      "path": "1-Daily/2025-02-17.md"
    },
    {
      "basename": "2025-02-11",
      "path": "1-Daily/2025-02-11.md"
    }
  ],
  "omittedPaths": [],
  "omittedTags": [],
  "updateOn": "file-open",
  "omitBookmarks": false
}